tests/__init__.py
tests/benchmark.py
tests/genducers.py
tests/transducer_tests.py
transducers/__init__.py
transducers/transducers.py
transducers-0.4.dev.dist-info/DESCRIPTION.rst
transducers-0.4.dev.dist-info/METADATA
transducers-0.4.dev.dist-info/metadata.json
transducers-0.4.dev.dist-info/RECORD
transducers-0.4.dev.dist-info/top_level.txt
transducers-0.4.dev.dist-info/WHEEL
