Metadata-Version: 2.0
Name: transducers
Version: 0.4.dev
Summary: Clojure Transducers implemented in Python
Home-page: https://github.com/cognitect-labs/transducers-python
Author: Cognitect
Author-email: UNKNOWN
License: UNKNOWN
Platform: UNKNOWN
